README.rst
setup.cfg
setup.py
ep_spread_sheet/__init__.py
ep_spread_sheet/google_sheet.py
ep_spread_sheet.egg-info/PKG-INFO
ep_spread_sheet.egg-info/SOURCES.txt
ep_spread_sheet.egg-info/dependency_links.txt
ep_spread_sheet.egg-info/requires.txt
ep_spread_sheet.egg-info/top_level.txt