Metadata-Version: 1.1
Name: ep-spread-sheet
Version: 1.0.2
Summary: A package for parsing google spread sheets
Home-page: https://github.com/dcjohnston/ep-spread-sheet
Author: Derek Johnston
Author-email: djohnston2014@gmail.com
License: MIT
Keywords: googlesheets spreadsheet parser
Platform: UNKNOWN
Classifier: Development Status :: 5 - Production/Stable
Classifier: Intended Audience :: Developers
Classifier: Topic :: Software Development :: Build Tools
Classifier: License :: OSI Approved :: MIT License
Classifier: Programming Language :: Python :: 2.7
